mopidy_choosmoos/__init__.py
mopidy_choosmoos/ext.conf
mopidy_choosmoos/frontend.py
mopidy_choosmoos/globals.py
mopidy_choosmoos/web.py
mopidy_choosmoos/interface/__init__.py
mopidy_choosmoos/interface/buttons.py
mopidy_choosmoos/interface/db.py
mopidy_choosmoos/interface/mopidy_core.py
mopidy_choosmoos/interface/mopidy_web.py
mopidy_choosmoos/interface/onboard_leds.py
mopidy_choosmoos/interface/rfid.py
mopidy_choosmoos/interface/sound.py
mopidy_choosmoos/interface/spotify_playlist.py
mopidy_choosmoos/static/app.js
mopidy_choosmoos/static/index.html
mopidy_choosmoos/utils/__init__.py
mopidy_choosmoos/utils/onboard_leds.py
mopidy_choosmoos/utils/pn7150.py
mopidy_choosmoos-1.0.0.dist-info/LICENSE
mopidy_choosmoos-1.0.0.dist-info/METADATA
mopidy_choosmoos-1.0.0.dist-info/WHEEL
mopidy_choosmoos-1.0.0.dist-info/entry_points.txt
mopidy_choosmoos-1.0.0.dist-info/top_level.txt
mopidy_choosmoos-1.0.0.dist-info/RECORD
